CHANGELOG.rst
LICENSE.txt
MANIFEST.in
README.rst
requirements-checks.txt
requirements-tests.txt
requirements.txt
setup.cfg
setup.py
docs/Makefile
docs/api.rst
docs/changelog.rst
docs/conf.py
docs/index.rst
docs/readme.rst
executor/__init__.py
executor/chroot.py
executor/cli.py
executor/concurrent.py
executor/contexts.py
executor/process.py
executor/schroot.py
executor/tcp.py
executor/tests.py
executor/ssh/__init__.py
executor/ssh/client.py
executor/ssh/server.py
metabolexecutor.egg-info/PKG-INFO
metabolexecutor.egg-info/SOURCES.txt
metabolexecutor.egg-info/dependency_links.txt
metabolexecutor.egg-info/entry_points.txt
metabolexecutor.egg-info/requires.txt
metabolexecutor.egg-info/top_level.txt